DOLOST/__init__.py
DOLOST/app.py
DOLOST/cli.py
DOLOST/context.py
DOLOST/version.py
DOLOST/blueprints/__init__.py
DOLOST/blueprints/api.py
DOLOST/blueprints/views.py
DOLOST/blueprints/websocket.py
DOLOST/decoyfiles/collector/collector.py
DOLOST/decoyfiles/collector/rsyslog.conf
DOLOST/decoyfiles/decoy_apache/DemoFinanceLogo.png
DOLOST/decoyfiles/decoy_apache/index.html
DOLOST/decoyfiles/decoy_apache/test.php
DOLOST/decoyfiles/decoy_mysql/config.inc.php
DOLOST/decoyfiles/decoy_ssh/welcome_banner.txt
DOLOST/dockerfiles_templates/Dockerfile-apache
DOLOST/dockerfiles_templates/Dockerfile-collector
DOLOST/dockerfiles_templates/Dockerfile-mysql
DOLOST/dockerfiles_templates/Dockerfile-ssh
DOLOST/services/__init__.py
DOLOST/services/activity.py
DOLOST/services/docker_manager.py
DOLOST/services/logger.py
DOLOST/static/imgs/full-logo.png
DOLOST/static/imgs/logo-dark.png
DOLOST/static/imgs/logo-light.png
DOLOST/static/js/bootstrap_toasts.js
DOLOST/static/js/docker_config_worker.js
DOLOST/static/js/operations_creator.js
DOLOST/static/js/theme_switcher.js
DOLOST/static/js/view_activities_worker.js
DOLOST/static/js/view_operations_worker.js
DOLOST/templates/base.html
DOLOST/templates/docker_client_config.html
DOLOST/templates/operations.html
DOLOST/templates/view_activity.html
DOLOST/templates/view_operation.html
DOLOST-1.2.dist-info/LICENSE
DOLOST-1.2.dist-info/METADATA
DOLOST-1.2.dist-info/WHEEL
DOLOST-1.2.dist-info/entry_points.txt
DOLOST-1.2.dist-info/top_level.txt
DOLOST-1.2.dist-info/RECORD
