Metadata-Version: 2.1
Name: DOLOST
Version: 1.2
Summary: Deceptive Operations: Lure, Observe, and Secure Tool
Home-page: https://github.com/Base4Security/DOLOS-T/
Author-email: idi@base4sec.com
Project-URL: Bug Tracker, https://github.com/Base4Security/DOLOS-T/issues
Classifier: Programming Language :: Python :: 3
Classifier: License :: OSI Approved :: GNU General Public License v3 (GPLv3)
Classifier: Topic :: Software Development :: Libraries :: Application Frameworks
Classifier: Operating System :: OS Independent
License-File: LICENSE
Requires-Dist: flask
Requires-Dist: docker
Requires-Dist: flask-socketio
Requires-Dist: gevent-websocket
